co_tools/__init__.py
co_tools/co_fasta.py
co_tools/co_fastq.py
co_tools/co_utils.py
co_tools/get_cpu_count.py
co_tools/get_dir_contents.py
co_tools/get_fasta_file.py
co_tools/get_fastq_pair.py
co_tools/get_fastqs.py
co_tools/get_groups.py
co_tools/get_logger.py
co_tools/get_pipeline_confirm.py
co_tools/get_read_direction.py
co_tools/get_read_pattern.py
co_tools/get_read_prefix.py
co_tools/get_rev_file.py
co_tools/set_log_msg.py
code_ocean_aux_tools-1.1.3.dist-info/METADATA
code_ocean_aux_tools-1.1.3.dist-info/WHEEL
code_ocean_aux_tools-1.1.3.dist-info/entry_points.txt
code_ocean_aux_tools-1.1.3.dist-info/licenses/LICENSE
code_ocean_aux_tools-1.1.3.dist-info/RECORD
