Metadata-Version: 2.1
Name: Code_Ocean_Aux_Tools
Version: 1.1.3
Summary: A suite of convenience tools for working with common bioinformatics files in Code Ocean capsules and pipelines.
Project-URL: Homepage, https://github.com/codeocean/co_aux_tools
Project-URL: Bug Tracker, https://github.com/codeocean/co_aux_tools/issues
Author-email: Frank Zappulla <frank@codeocean.com>
Maintainer-email: Frank Zappulla <frank@codeocean.com>
License-File: LICENSE
Classifier: License :: OSI Approved :: MIT License
Classifier: Operating System :: OS Independent
Classifier: Programming Language :: Python :: 3
Requires-Python: >=3.8
Requires-Dist: typer>=0.9.0
